fsl_pipe/__init__.py
fsl_pipe/datalad.py
fsl_pipe/job.py
fsl_pipe/pipeline.py
fsl_pipe/testing.py
fsl_pipe-1.3.0.dist-info/METADATA
fsl_pipe-1.3.0.dist-info/WHEEL
fsl_pipe-1.3.0.dist-info/licenses/LICENSE
fsl_pipe-1.3.0.dist-info/RECORD
