Metadata-Version: 2.4
Name: fsl-pipe
Version: 1.3.0
Summary: Declarative pipelines based on Filetrees
Project-URL: Homepage, https://git.fmrib.ox.ac.uk/fsl/fsl-pipe
Project-URL: Documentation, https://open.win.ox.ac.uk/pages/fsl/fsl-pipe
Project-URL: Repository, https://git.fmrib.ox.ac.uk/fsl/fsl-pipe
Project-URL: Issues, https://git.fmrib.ox.ac.uk/fsl/fsl-pipe/-/issues
Project-URL: Changelog, https://git.fmrib.ox.ac.uk/fsl/fsl-pipe/-/blob/main/CHANGELOG.md
Author-email: Michiel Cottaar <michiel.cottaar@ndcn.ox.ac.uk>
License: MIT License
License-File: LICENSE
Keywords: neuroimage,pipeline
Requires-Python: >=3.10
Requires-Dist: dask
Requires-Dist: file-tree>=1.5
Requires-Dist: fsl-sub
Requires-Dist: fslpy
Requires-Dist: graphviz
Requires-Dist: loguru
Requires-Dist: wcmatch>=10.0
Requires-Dist: xarray
